[
  {
    "slug": "esb-pakkinn-er-galopinn",
    "article_title": "ESB-pakkinn er galopinn",
    "article_source": "Vísir",
    "article_url": null,
    "article_author": "Bergþór Ólason",
    "article_date": "2026-03-09",
    "analysis_date": "2026-03-09",
    "summary": "Greining á 16 fullyrðingum. Niðurstöður: 7 stutt að hluta, 7 óstaðfestanlegar, 2 villandi. Innramming: sterklega gegn ESB-aðild. Heildarsamhengi: 15%.",
    "claim_count": 16,
    "verdict_counts": {
      "partially_supported": 7,
      "unverifiable": 7,
      "misleading": 2
    },
    "dominant_category": "eea_eu_law",
    "categories": [
      "eea_eu_law",
      "other",
      "party_positions",
      "precedents"
    ],
    "speakers": [
      {
        "name": "Bergþór Ólason",
        "party": "Miðflokkurinn",
        "stance": "anti_eu"
      },
      {
        "name": "Viðreisn",
        "party": null,
        "stance": "pro_eu"
      },
      {
        "name": "Ríkisútvarpið",
        "party": null,
        "stance": "neutral"
      },
      {
        "name": "Heather Grabbe",
        "party": null,
        "stance": "neutral"
      },
      {
        "name": "Bruegel",
        "party": null,
        "stance": "neutral"
      },
      {
        "name": "Stefan Füle",
        "party": null,
        "stance": "neutral"
      },
      {
        "name": "Össur Skarphéðinsson",
        "party": null,
        "stance": "pro_eu"
      },
      {
        "name": "Miðflokkurinn",
        "party": null,
        "stance": "anti_eu"
      },
      {
        "name": "Björn Malmquist",
        "party": null,
        "stance": "neutral"
      }
    ]
  },
  {
    "slug": "flott-embaetti-i-bodi-fyrir-esb-riki",
    "article_title": "Flott embætti í boði fyrir ESB ríki",
    "article_source": "Vísir",
    "article_url": null,
    "article_author": "Diljá Mist Einarsdóttir",
    "article_date": "2026-03-09",
    "analysis_date": "2026-03-09",
    "summary": "Greindar voru 13 fullyrðingar. Niðurstöður: 5 ósannreynanlegar, 4 studdar af heimildum, 3 studdar að hluta, 1 villandi. Framsetnng: hallast gegn ESB-aðild. Heildarumfjöllun: 15%.",
    "claim_count": 13,
    "verdict_counts": {
      "partially_supported": 3,
      "supported": 4,
      "misleading": 1,
      "unverifiable": 5
    },
    "dominant_category": "sovereignty",
    "categories": [
      "eea_eu_law",
      "fisheries",
      "party_positions",
      "precedents",
      "sovereignty"
    ],
    "speakers": [
      {
        "name": "Diljá Mist Einarsdóttir",
        "party": "Sjálfstæðisflokkurinn",
        "stance": "anti_eu"
      },
      {
        "name": "Samfylkingin",
        "party": null,
        "stance": "pro_eu"
      },
      {
        "name": "Viðreisn",
        "party": null,
        "stance": "pro_eu"
      },
      {
        "name": "Flokkur fólksins",
        "party": null,
        "stance": "pro_eu"
      },
      {
        "name": "Jóhanna Sigurðardóttir",
        "party": "Samfylkingin",
        "stance": "pro_eu"
      },
      {
        "name": "Evrópusambandið",
        "party": null,
        "stance": "neutral"
      },
      {
        "name": "Sjálfstæðisflokkurinn",
        "party": null,
        "stance": "anti_eu"
      },
      {
        "name": "Gerhard Schröder",
        "party": null,
        "stance": "neutral"
      }
    ]
  },
  {
    "slug": "landbunadarstefna-esb-henti-islenskum-landbunadi-illa",
    "article_title": "Landbúnaðarstefna ESB henti íslenskum landbúnaði illa",
    "article_source": "Vísir",
    "article_url": null,
    "article_author": "Berghildur Erla Bernharðsdóttir",
    "article_date": "2026-03-09",
    "analysis_date": "2026-03-09",
    "summary": "Greindar 16 fullyrðingar. Niðurstöður: 7 stutt að hluta, 4 stutt af heimildum, 3 ekki hægt að sannreyna, 1 villandi, 1 ekki stutt. Sjónarhorn: hallar á ESB-neikvæða hlið. Heildstæðni: 30%.",
    "claim_count": 16,
    "verdict_counts": {
      "partially_supported": 7,
      "supported": 4,
      "unverifiable": 3,
      "misleading": 1,
      "unsupported": 1
    },
    "dominant_category": "agriculture",
    "categories": [
      "agriculture",
      "org_positions",
      "party_positions",
      "precedents",
      "sovereignty"
    ],
    "speakers": [
      {
        "name": "Berghildur Erla Bernharðsdóttir",
        "party": null,
        "stance": "neutral"
      },
      {
        "name": "Miðflokkurinn",
        "party": null,
        "stance": "anti_eu"
      },
      {
        "name": "Formaður Miðflokksins",
        "party": "Miðflokkurinn",
        "stance": "anti_eu"
      },
      {
        "name": "Sjálfstæðisflokkurinn",
        "party": null,
        "stance": "anti_eu"
      },
      {
        "name": "Formaður Sjálfstæðisflokksins",
        "party": "Sjálfstæðisflokkurinn",
        "stance": "anti_eu"
      },
      {
        "name": "Margrét Ágústa Sigurðardóttir",
        "party": null,
        "stance": "anti_eu"
      },
      {
        "name": "Bændasamtökin",
        "party": null,
        "stance": "anti_eu"
      },
      {
        "name": "Evrópusambandið",
        "party": null,
        "stance": "neutral"
      },
      {
        "name": "Utanríkisráðherra",
        "party": null,
        "stance": "pro_eu"
      }
    ]
  },
  {
    "slug": "vid-hefdum-nad-meiri-arangri-med-thvi-ad-vera-innan-evropusambandsins",
    "article_title": "„Við hefðum náð meiri árangri með því að vera innan Evrópusambandsins“",
    "article_source": "Vísir",
    "article_url": null,
    "article_author": "Silja Rún Sigurbjörnsdóttir",
    "article_date": "2026-03-08",
    "analysis_date": "2026-03-09",
    "summary": "Greindar 17 fullyrðingar. Niðurstöður: 7 stutt að hluta, 6 ekki hægt að sannreyna, 3 stutt af heimildum, 1 ekki stutt. Sjónarhorn: hallar á ESB-jákvæða hlið. Heildstæðni: 25%.",
    "claim_count": 17,
    "verdict_counts": {
      "unverifiable": 6,
      "partially_supported": 7,
      "unsupported": 1,
      "supported": 3
    },
    "dominant_category": "eea_eu_law",
    "categories": [
      "eea_eu_law",
      "fisheries",
      "party_positions",
      "sovereignty",
      "trade"
    ],
    "speakers": [
      {
        "name": "Þorgerður Katrín Gunnarsdóttir",
        "party": null,
        "stance": "pro_eu"
      },
      {
        "name": "Silja Rún Sigurbjörnsdóttir",
        "party": null,
        "stance": "neutral"
      },
      {
        "name": "Evrópusambandið",
        "party": null,
        "stance": "neutral"
      },
      {
        "name": "Icelandair",
        "party": null,
        "stance": "neutral"
      },
      {
        "name": "Formenn ríkisstjórnarflokkanna",
        "party": null,
        "stance": "pro_eu"
      }
    ]
  },
  {
    "slug": "thridjungur-andvigur-atkvaedagreidslunni",
    "article_title": "Þriðjungur andvígur atkvæðagreiðslunni",
    "article_source": "Vísir",
    "article_url": "https://www.visir.is/g/20262853438d/thridjungur-andvigur-atkvaedagreidslunni",
    "article_author": "Silja Rún Sigurbjörnsdóttir",
    "article_date": "2026-03-09",
    "analysis_date": "2026-03-10",
    "summary": "Greindar 18 fullyrðingar. Niðurstöður: 14 stutt af heimildum, 4 stutt að hluta. Sjónarhorn: hlutlaus en ófullnægjandi. Heildstæðni: 45%.",
    "claim_count": 18,
    "verdict_counts": {
      "supported": 14,
      "partially_supported": 4
    },
    "dominant_category": "polling",
    "categories": [
      "party_positions",
      "polling",
      "sovereignty"
    ],
    "speakers": [
      {
        "name": "Gallup",
        "party": null,
        "stance": "neutral"
      },
      {
        "name": "Silja Rún Sigurbjörnsdóttir",
        "party": null,
        "stance": "neutral"
      },
      {
        "name": "Viðreisn",
        "party": null,
        "stance": "pro_eu"
      },
      {
        "name": "Miðflokkurinn",
        "party": null,
        "stance": "anti_eu"
      },
      {
        "name": "Sjálfstæðisflokkurinn",
        "party": null,
        "stance": "anti_eu"
      },
      {
        "name": "Framsóknarflokkurinn",
        "party": null,
        "stance": "mixed"
      }
    ]
  },
  {
    "slug": "trump-sagdur-beita-ser-i-esb-umraedunni-her-a-landi",
    "article_title": "Trump sagður beita sér í ESB-umræðunni hér á landi",
    "article_source": "Vísir",
    "article_url": "https://www.visir.is/g/20262853660d/trump-sagdur-beita-ser-i-esb-umraedunni-her-a-landi",
    "article_author": "Samúel Karl Ólason",
    "article_date": "2026-03-10",
    "analysis_date": "2026-03-10",
    "summary": "Greindar 21 fullyrðingar. Niðurstöður: 11 ekki hægt að sannreyna, 5 stutt að hluta, 3 stutt af heimildum, 1 ekki stutt, 1 villandi. Sjónarhorn: hallar á ESB-neikvæða hlið. Heildstæðni: 25%.",
    "claim_count": 21,
    "verdict_counts": {
      "unverifiable": 11,
      "partially_supported": 5,
      "unsupported": 1,
      "supported": 3,
      "misleading": 1
    },
    "dominant_category": "sovereignty",
    "categories": [
      "party_positions",
      "precedents",
      "sovereignty",
      "trade"
    ],
    "speakers": [
      {
        "name": "Ríkisstjórn Donalds Trump",
        "party": null,
        "stance": "anti_eu"
      },
      {
        "name": "Altinget.no",
        "party": null,
        "stance": "neutral"
      },
      {
        "name": "Nigel Farage",
        "party": "Reform",
        "stance": "anti_eu"
      },
      {
        "name": "Miðflokkurinn",
        "party": null,
        "stance": "anti_eu"
      },
      {
        "name": "Sjálfstæðisflokkurinn",
        "party": null,
        "stance": "mixed"
      },
      {
        "name": "Billy Long",
        "party": null,
        "stance": "neutral"
      },
      {
        "name": "Katrín Jakobsdóttir",
        "party": "Vinstrihreyfingin - grænt framboð",
        "stance": "pro_eu"
      },
      {
        "name": "Donald Trump",
        "party": null,
        "stance": "anti_eu"
      },
      {
        "name": "Þorgerður Katrín Gunnarsdóttir",
        "party": "Framsóknarflokkurinn",
        "stance": "neutral"
      },
      {
        "name": "Evrópusambandið",
        "party": null,
        "stance": "neutral"
      }
    ]
  },
  {
    "slug": "engin-fordaemi-fyrir-leid-islands-i-att-ad-esb",
    "article_title": "Engin fordæmi fyrir leið Íslands í átt að ESB",
    "article_source": "RÚV",
    "article_url": "https://www.ruv.is/frettir/innlent/2026-03-10-engin-fordaemi-fyrir-leid-islands-i-att-ad-esb-469374/",
    "article_author": "Mist Þormóðsdóttir Grönvold",
    "article_date": "2026-03-10",
    "analysis_date": "2026-03-10",
    "summary": "Greindar 21 fullyrðingar. Niðurstöður: 10 stutt að hluta, 10 stutt af heimildum, 1 ekki hægt að sannreyna. Sjónarhorn: hlutlaus en ófullnægjandi. Heildstæðni: 25%.",
    "claim_count": 21,
    "verdict_counts": {
      "partially_supported": 10,
      "supported": 10,
      "unverifiable": 1
    },
    "dominant_category": "eea_eu_law",
    "categories": [
      "eea_eu_law",
      "other",
      "precedents",
      "sovereignty"
    ],
    "speakers": [
      {
        "name": "Vilborg Ása Guðjónsdóttir",
        "party": null,
        "stance": "neutral"
      },
      {
        "name": "Evrópusambandið",
        "party": null,
        "stance": "neutral"
      },
      {
        "name": "Mist Þormóðsdóttir Grönvold",
        "party": null,
        "stance": "neutral"
      }
    ]
  },
  {
    "slug": "esb-adild-hefdi-veruleg-neikvaed-ahrif-a-hagsmuni-islenskra-baenda",
    "article_title": "ESB aðild hefði veruleg neikvæð áhrif á hagsmuni íslenskra bænda",
    "article_source": "RÚV",
    "article_url": "https://www.ruv.is/frettir/innlent/2026-03-07-esb-adild-hefdi-veruleg-neikvaed-ahrif-a-hagsmuni-islenskra-baenda-469093/",
    "article_author": "Eva Björk Benediktsdóttir",
    "article_date": "2026-03-07",
    "analysis_date": "2026-03-10",
    "summary": "Greindar 6 fullyrðingar. Niðurstöður: 1 villandi, 4 stutt að hluta, 1 ekki hægt að sannreyna. Sjónarhorn: hallar á ESB-neikvæða hlið. Heildstæðni: 20%.",
    "claim_count": 6,
    "verdict_counts": {
      "partially_supported": 4,
      "misleading": 1,
      "unverifiable": 1
    },
    "dominant_category": "agriculture",
    "categories": [
      "agriculture",
      "org_positions",
      "sovereignty"
    ],
    "speakers": [
      {
        "name": "Trausti Hjálmarsson",
        "party": null,
        "stance": "anti_eu"
      },
      {
        "name": "Bændasamtök Íslands",
        "party": null,
        "stance": "anti_eu"
      }
    ]
  },
  {
    "slug": "raeda-tharf-alla-kaflana-a-nyjan-leik",
    "article_title": "Ræða þarf alla kaflana á nýjan leik",
    "article_source": "Morgunblaðið",
    "article_url": "https://www.mbl.is/frettir/innlent/2026/03/10/raeda_tharf_alla_kaflana_a_nyjan_leik/",
    "article_author": "Morgunblaðið (viðtal við Ernu Bjarnadóttir hagfræðing)",
    "article_date": "2026-03-10",
    "analysis_date": "2026-03-10",
    "summary": "Greindar 38 fullyrðingar. Niðurstöður: 22 stutt af heimildum, 8 stutt að hluta, 5 ekki hægt að sannreyna, 2 ekki stutt, 1 villandi. Sjónarhorn: hallar á ESB-neikvæða hlið. Heildstæðni: 35%.",
    "claim_count": 38,
    "verdict_counts": {
      "unverifiable": 5,
      "partially_supported": 8,
      "supported": 22,
      "misleading": 1,
      "unsupported": 2
    },
    "dominant_category": "agriculture",
    "categories": [
      "agriculture",
      "currency",
      "eea_eu_law",
      "fisheries",
      "trade"
    ],
    "speakers": [
      {
        "name": "Erna Bjarnadóttir",
        "party": null,
        "stance": "neutral"
      },
      {
        "name": "Evrópusambandið",
        "party": null,
        "stance": "neutral"
      },
      {
        "name": "Bændasamtökin",
        "party": null,
        "stance": "anti_eu"
      },
      {
        "name": "Morgunblaðið",
        "party": null,
        "stance": "neutral"
      }
    ]
  },
  {
    "slug": "idnadurinn-forherdist-i-andstodu-gegn-esb",
    "article_title": "Iðnaðurinn forherðist í andstöðu gegn ESB",
    "article_source": "Vísir",
    "article_url": "https://www.visir.is/g/20262853308d/idnadurinn-forherdist-i-andstodu-gegn-esb",
    "article_author": "Kjartan Kjartansson",
    "article_date": "2026-03-09",
    "analysis_date": "2026-03-10",
    "summary": "Greindar 13 fullyrðingar .",
    "claim_count": 13,
    "verdict_counts": {
      "supported": 7,
      "partially_supported": 3,
      "unverifiable": 3
    },
    "dominant_category": "org_positions",
    "categories": [
      "org_positions",
      "sovereignty"
    ],
    "speakers": [
      {
        "name": "Kjartan Kjartansson",
        "party": null,
        "stance": "neutral"
      },
      {
        "name": "Samtök iðnaðarins",
        "party": null,
        "stance": "neutral"
      },
      {
        "name": "Alþingi",
        "party": null,
        "stance": "neutral"
      },
      {
        "name": "Ríkisstjórnin",
        "party": null,
        "stance": "pro_eu"
      }
    ]
  },
  {
    "slug": "ekki-vist-hvernig-evropusambandid-bregst-vid",
    "article_title": "Ekki víst hvernig Evrópusambandið bregst við",
    "article_source": "Morgunblaðið",
    "article_url": "https://www.mbl.is/frettir/innlent/2026/03/09/ekki_vist_hvernig_evropusambandid_bregst_vid/",
    "article_author": "Morgunblaðið",
    "article_date": "2026-03-09",
    "analysis_date": "2026-03-10",
    "summary": "Greindar 14 fullyrðingar .",
    "claim_count": 14,
    "verdict_counts": {
      "partially_supported": 4,
      "supported": 3,
      "unverifiable": 6,
      "unsupported": 1
    },
    "dominant_category": "eea_eu_law",
    "categories": [
      "eea_eu_law",
      "party_positions",
      "sovereignty"
    ],
    "speakers": [
      {
        "name": "Pavel Bartoszek",
        "party": "Viðreisn",
        "stance": "pro_eu"
      },
      {
        "name": "Evrópusambandið",
        "party": null,
        "stance": "neutral"
      },
      {
        "name": "Morgunblaðið",
        "party": null,
        "stance": "neutral"
      },
      {
        "name": "Jens Garðar Helgason",
        "party": "Sjálfstæðisflokkurinn",
        "stance": "anti_eu"
      },
      {
        "name": "Ríkisstjórnin",
        "party": null,
        "stance": "pro_eu"
      },
      {
        "name": "Björn Bjarnason",
        "party": "Sjálfstæðisflokkurinn",
        "stance": "anti_eu"
      },
      {
        "name": "Utanríkisráðuneytið",
        "party": null,
        "stance": "neutral"
      }
    ]
  },
  {
    "slug": "390-000-hektarar-af-landbunadarlandi-breytast-i-skog-og-votlendi",
    "article_title": "390.000 hektarar af landbúnaðarlandi breytast í skóg og votlendi",
    "article_source": "Vísir",
    "article_url": "https://www.visir.is/g/20262853352d/390.000-hektarar-af-landbunadarlandi-breytast-i-skog-og-votlendi-landbunadur-naesta-stora-loftslagsverkefni-dana",
    "article_author": null,
    "article_date": "2026-03-09",
    "analysis_date": "2026-03-10",
    "summary": "Greindar 25 fullyrðingar .",
    "claim_count": 25,
    "verdict_counts": {
      "unverifiable": 3,
      "partially_supported": 12,
      "supported": 9,
      "misleading": 1
    },
    "dominant_category": "agriculture",
    "categories": [
      "agriculture",
      "precedents",
      "trade"
    ],
    "speakers": [
      {
        "name": null,
        "party": null,
        "stance": "pro_eu"
      },
      {
        "name": "Climate Change Performance Index",
        "party": null,
        "stance": "neutral"
      },
      {
        "name": "Dönsk stjórnvöld",
        "party": null,
        "stance": "neutral"
      },
      {
        "name": "Evrópusambandið",
        "party": null,
        "stance": "neutral"
      }
    ]
  },
  {
    "slug": "snorri-segir-husnaedi-verda-jafndyrt-thott-vextir-laekki",
    "article_title": "Snorri segir húsnæði verða jafndýrt þótt vextir lækki",
    "article_source": "Heimildin",
    "article_url": "https://heimildin.is/grein/26323/snorri-segir-husnaedi-verda-jafndyrt-thott-vextir-laekki/",
    "article_author": null,
    "article_date": "2026-03-09",
    "analysis_date": "2026-03-10",
    "summary": "Greindar 16 fullyrðingar .",
    "claim_count": 16,
    "verdict_counts": {
      "supported": 4,
      "partially_supported": 10,
      "unverifiable": 1,
      "misleading": 1
    },
    "dominant_category": "housing",
    "categories": [
      "currency",
      "eea_eu_law",
      "housing",
      "party_positions",
      "precedents",
      "sovereignty",
      "trade"
    ],
    "speakers": [
      {
        "name": "Heimildin fréttastofa",
        "party": null,
        "stance": "neutral"
      },
      {
        "name": "Seðlabanki Evrópu",
        "party": null,
        "stance": "neutral"
      },
      {
        "name": "Snorri Másson",
        "party": "Miðflokkurinn",
        "stance": "anti_eu"
      },
      {
        "name": "Miðflokkurinn",
        "party": null,
        "stance": "anti_eu"
      },
      {
        "name": "Sjálfstæðisflokkurinn",
        "party": null,
        "stance": "anti_eu"
      },
      {
        "name": "Framsóknarflokkurinn",
        "party": null,
        "stance": "anti_eu"
      },
      {
        "name": "Flokkur fólksins",
        "party": null,
        "stance": "anti_eu"
      },
      {
        "name": "Evrópusambandið",
        "party": null,
        "stance": "neutral"
      }
    ]
  },
  {
    "slug": "segja-samningavidraedur-vera-villandi-hugtak",
    "article_title": "Segja „samningaviðræður“ vera villandi hugtak",
    "article_source": "Morgunblaðið",
    "article_url": "https://www.mbl.is/frettir/erlent/2026/03/09/segja_8222_samninga_vidraedur_8220_vera_villandi_hu/",
    "article_author": null,
    "article_date": "2026-03-09",
    "analysis_date": "2026-03-10",
    "summary": "Greindar 6 fullyrðingar .",
    "claim_count": 6,
    "verdict_counts": {
      "supported": 4,
      "misleading": 1,
      "partially_supported": 1
    },
    "dominant_category": "eea_eu_law",
    "categories": [
      "eea_eu_law"
    ],
    "speakers": [
      {
        "name": "Evrópusambandið",
        "party": null,
        "stance": "neutral"
      }
    ]
  },
  {
    "slug": "bandarikjamonnum-hugnast-ekki-innganga-islands-i-esb",
    "article_title": "Bandaríkjamönnum hugnast ekki innganga Íslands í ESB",
    "article_source": "Heimildin",
    "article_url": "https://heimildin.is/grein/26326/bandarikjamonnum-hugnast-ekki-innganga-islands-i-esb/",
    "article_author": null,
    "article_date": "2026-03-09",
    "analysis_date": "2026-03-10",
    "summary": "Greindar 9 fullyrðingar .",
    "claim_count": 9,
    "verdict_counts": {
      "partially_supported": 6,
      "unverifiable": 1,
      "misleading": 2
    },
    "dominant_category": "party_positions",
    "categories": [
      "other",
      "party_positions",
      "sovereignty",
      "trade"
    ],
    "speakers": [
      {
        "name": "Donald Trump",
        "party": "Repúblikanaflokkurinn",
        "stance": "anti_eu"
      },
      {
        "name": "Altinget.no",
        "party": null,
        "stance": "neutral"
      },
      {
        "name": "Ríkisstjórn Bandaríkjanna",
        "party": null,
        "stance": "anti_eu"
      },
      {
        "name": "Nigel Farage",
        "party": "UKIP",
        "stance": "anti_eu"
      },
      {
        "name": "Miðflokkurinn",
        "party": null,
        "stance": "anti_eu"
      },
      {
        "name": "Repúblikanaflokkurinn",
        "party": null,
        "stance": "anti_eu"
      },
      {
        "name": "UKIP",
        "party": null,
        "stance": "anti_eu"
      },
      {
        "name": "Heimildin",
        "party": null,
        "stance": "neutral"
      }
    ]
  },
  {
    "slug": "thjodin-a-badum-attum-um-vidraedur-52-gegn-48",
    "article_title": "Þjóðin á báðum áttum um viðræður: 52% gegn 48%",
    "article_source": "Morgunblaðið",
    "article_url": "https://www.mbl.is/frettir/innlent/2026/03/09/thjodin_a_badum_attum_um_vidraedur_52_prosent_gegn_/",
    "article_author": null,
    "article_date": "2026-03-09",
    "analysis_date": "2026-03-10",
    "summary": "Greindar 21 fullyrðingar .",
    "claim_count": 21,
    "verdict_counts": {
      "supported": 18,
      "partially_supported": 3
    },
    "dominant_category": "polling",
    "categories": [
      "party_positions",
      "polling"
    ],
    "speakers": [
      {
        "name": "Ritstjórn mbl.is",
        "party": null,
        "stance": "neutral"
      },
      {
        "name": "Gallup",
        "party": null,
        "stance": "neutral"
      },
      {
        "name": "Evrópusambandið",
        "party": null,
        "stance": "neutral"
      },
      {
        "name": "Viðreisn",
        "party": null,
        "stance": "pro_eu"
      },
      {
        "name": "Samfylkingin",
        "party": null,
        "stance": "pro_eu"
      },
      {
        "name": "Flokkur fólksins",
        "party": null,
        "stance": "mixed"
      },
      {
        "name": "Miðflokkurinn",
        "party": null,
        "stance": "anti_eu"
      },
      {
        "name": "Sjálfstæðisflokkurinn",
        "party": null,
        "stance": "mixed"
      }
    ]
  },
  {
    "slug": "ad-kljufa-thjodina-med-tilfinningathrunginni-spurningu",
    "article_title": "Að kljúfa þjóðina með tilfinningaþrunginni spurningu",
    "article_source": "Vísir",
    "article_url": "https://www.visir.is/g/20262853502d/ad-kljufa-thjodina-med-tilfinningathrunginni-spurningu",
    "article_author": null,
    "article_date": "2026-03-09",
    "analysis_date": "2026-03-10",
    "summary": "Greindar 14 fullyrðingar .",
    "claim_count": 14,
    "verdict_counts": {
      "partially_supported": 4,
      "supported": 5,
      "misleading": 1,
      "unverifiable": 4
    },
    "dominant_category": "party_positions",
    "categories": [
      "currency",
      "energy",
      "housing",
      "other",
      "party_positions",
      "precedents"
    ],
    "speakers": [
      {
        "name": "Kristrún Frostadóttir",
        "party": "Samfylkingin",
        "stance": "pro_eu"
      },
      {
        "name": "Guðrún Hafsteinsdóttir",
        "party": "Sjálfstæðisflokkurinn",
        "stance": "anti_eu"
      },
      {
        "name": "Evrópusambandið",
        "party": null,
        "stance": "neutral"
      },
      {
        "name": "NATO",
        "party": null,
        "stance": "neutral"
      },
      {
        "name": "Sjálfstæðisflokkurinn",
        "party": null,
        "stance": "anti_eu"
      }
    ]
  },
  {
    "slug": "treystu-thjodinni-opid-bref-til-forsaetisradherra-islands",
    "article_title": "Treystu þjóðinni — Opið bréf til forsætisráðherra Íslands",
    "article_source": "Vísir",
    "article_url": "https://www.visir.is/g/20262853497d/treystu-thjodinni.-thu-ert-med-tromp-a-hendi-opid-bref-til-forsaetisradherra-islands",
    "article_author": null,
    "article_date": "2026-03-09",
    "analysis_date": "2026-03-10",
    "summary": "Greindar 12 fullyrðingar .",
    "claim_count": 12,
    "verdict_counts": {
      "supported": 5,
      "unverifiable": 4,
      "partially_supported": 2,
      "misleading": 1
    },
    "dominant_category": "sovereignty",
    "categories": [
      "eea_eu_law",
      "fisheries",
      "other",
      "sovereignty"
    ],
    "speakers": [
      {
        "name": "Stjórnarskrárfélagið",
        "party": null,
        "stance": "mixed"
      },
      {
        "name": "Alþingi",
        "party": null,
        "stance": "neutral"
      },
      {
        "name": "Ríkisstjórnin",
        "party": null,
        "stance": "neutral"
      },
      {
        "name": "Vigdís Finnbogadóttir",
        "party": null,
        "stance": "neutral"
      },
      {
        "name": "Evrópusambandið",
        "party": null,
        "stance": "neutral"
      }
    ]
  },
  {
    "slug": "thrir-hopar-sem-myndu-hagnast-mest-a-adild-islands-ad-evropusambandinu",
    "article_title": "Þrír hópar sem myndu hagnast mest á aðild Íslands að Evrópusambandinu",
    "article_source": "Vísir",
    "article_url": null,
    "article_author": "**Magnús Árni Skjöld Magnússon",
    "article_date": "2026-03-07",
    "analysis_date": "2026-03-10",
    "summary": "Greindar 23 fullyrðingar .",
    "claim_count": 23,
    "verdict_counts": {
      "supported": 10,
      "partially_supported": 9,
      "misleading": 3,
      "unverifiable": 1
    },
    "dominant_category": "currency",
    "categories": [
      "agriculture",
      "currency",
      "eea_eu_law",
      "fisheries",
      "org_positions",
      "party_positions",
      "precedents",
      "sovereignty",
      "trade"
    ],
    "speakers": [
      {
        "name": "Magnús Árni Skjöld Magnússon",
        "party": null,
        "stance": "pro_eu"
      },
      {
        "name": "Evrópusambandið",
        "party": null,
        "stance": "neutral"
      },
      {
        "name": "Evrópuhreyfingin",
        "party": null,
        "stance": "pro_eu"
      }
    ]
  },
  {
    "slug": "bjorn-hrekur-fullyrdingu-um-afdrif-sjavaraudlinda-islendinga-i-esb",
    "article_title": "Björn hrekur fullyrðingu um afdrif sjávarauðlinda Íslendinga í ESB",
    "article_source": null,
    "article_url": null,
    "article_author": null,
    "article_date": "2026-03-07",
    "analysis_date": "2026-03-10",
    "summary": "Greindar 15 fullyrðingar. Niðurstöður: 10 stutt að hluta, 3 ekki hægt að sannreyna, 2 stutt af heimildum. Sjónarhorn: hallar á ESB-jákvæða hlið. Heildstæðni: 30%.",
    "claim_count": 15,
    "verdict_counts": {
      "partially_supported": 10,
      "supported": 2,
      "unverifiable": 3
    },
    "dominant_category": "fisheries",
    "categories": [
      "fisheries",
      "polling"
    ],
    "speakers": [
      {
        "name": "Bjorn Levi Gunnarsson",
        "party": "Piratar",
        "stance": "pro_eu"
      },
      {
        "name": "Evrópusambandið",
        "party": null,
        "stance": "neutral"
      },
      {
        "name": "DV",
        "party": null,
        "stance": "neutral"
      },
      {
        "name": "Íslenska stórútgerðin",
        "party": null,
        "stance": "anti_eu"
      }
    ]
  },
  {
    "slug": "esb-adild-hefdi-veruleg-neikvaed-ahrif-a-hagsmuni-islenskra-baenda",
    "article_title": "ESB aðild hefði veruleg neikvæð áhrif á hagsmuni íslenskra bænda",
    "article_source": "RÚV",
    "article_url": null,
    "article_author": null,
    "article_date": "2026-03-07",
    "analysis_date": "2026-03-10",
    "summary": "Greindar 8 fullyrðingar. Niðurstöður: 3 stutt af heimildum, 2 stutt að hluta, 2 villandi, 1 ekki hægt að sannreyna. Sjónarhorn: hallar á ESB-neikvæða hlið. Heildstæðni: 30%.",
    "claim_count": 8,
    "verdict_counts": {
      "supported": 3,
      "unverifiable": 1,
      "partially_supported": 2,
      "misleading": 2
    },
    "dominant_category": "agriculture",
    "categories": [
      "agriculture",
      "org_positions",
      "trade"
    ],
    "speakers": [
      {
        "name": "Trausti Hjálmarsson",
        "party": null,
        "stance": "anti_eu"
      },
      {
        "name": "Bændasamtök Íslands",
        "party": null,
        "stance": "anti_eu"
      },
      {
        "name": "Evrópusambandið",
        "party": null,
        "stance": "neutral"
      }
    ]
  }
]