{
  "slug": "140-19",
  "title_slug": "flutningur-landhelgisgaeslunnar-til-reykjanesbaejar",
  "session": 140,
  "issue_nr": "19",
  "issue_title": "Flutningur Landhelgisgæslunnar til Reykjanesbæjar",
  "speech_count": 21,
  "speaker_count": 6,
  "total_words": 0,
  "first_date": "2011-11-01",
  "last_date": "2011-11-01",
  "althingi_url": "https://www.althingi.is/thingstorf/thingmalalistar-eftir-thingum/ferill/?ltg=140&mnr=19",
  "parties": [],
  "speakers": [
    {
      "name": "Mörður Árnason",
      "party": null,
      "speech_count": 7,
      "total_words": 0
    },
    {
      "name": "Oddný G. Harðardóttir",
      "party": null,
      "speech_count": 3,
      "total_words": 0
    },
    {
      "name": "Ragnheiður E. Árnadóttir",
      "party": null,
      "speech_count": 5,
      "total_words": 0
    },
    {
      "name": "Árni Johnsen",
      "party": null,
      "speech_count": 3,
      "total_words": 0
    },
    {
      "name": "Ögmundur Jónasson",
      "party": null,
      "speech_count": 2,
      "total_words": 0
    },
    {
      "name": "Þuríður Backman",
      "party": null,
      "speech_count": 1,
      "total_words": 0
    }
  ],
  "speeches": [
    {
      "speech_id": "rad20111101T160556",
      "speaker": "Oddný G. Harðardóttir",
      "party": null,
      "date": "2011-11-01",
      "started": "2011-11-01T16:05:56",
      "speech_type": "flutningsræða",
      "word_count": null,
      "excerpt": null
    },
    {
      "speech_id": "rad20111101T161124",
      "speaker": "Mörður Árnason",
      "party": null,
      "date": "2011-11-01",
      "started": "2011-11-01T16:11:24",
      "speech_type": "andsvar",
      "word_count": null,
      "excerpt": null
    },
    {
      "speech_id": "rad20111101T161307",
      "speaker": "Oddný G. Harðardóttir",
      "party": null,
      "date": "2011-11-01",
      "started": "2011-11-01T16:13:07",
      "speech_type": "andsvar",
      "word_count": null,
      "excerpt": null
    },
    {
      "speech_id": "rad20111101T161522",
      "speaker": "Mörður Árnason",
      "party": null,
      "date": "2011-11-01",
      "started": "2011-11-01T16:15:22",
      "speech_type": "andsvar",
      "word_count": null,
      "excerpt": null
    },
    {
      "speech_id": "rad20111101T161735",
      "speaker": "Oddný G. Harðardóttir",
      "party": null,
      "date": "2011-11-01",
      "started": "2011-11-01T16:17:35",
      "speech_type": "andsvar",
      "word_count": null,
      "excerpt": null
    },
    {
      "speech_id": "rad20111101T161947",
      "speaker": "Mörður Árnason",
      "party": null,
      "date": "2011-11-01",
      "started": "2011-11-01T16:19:47",
      "speech_type": "ræða",
      "word_count": null,
      "excerpt": null
    },
    {
      "speech_id": "rad20111101T163021",
      "speaker": "Árni Johnsen",
      "party": null,
      "date": "2011-11-01",
      "started": "2011-11-01T16:30:21",
      "speech_type": "andsvar",
      "word_count": null,
      "excerpt": null
    },
    {
      "speech_id": "rad20111101T163236",
      "speaker": "Þuríður Backman",
      "party": null,
      "date": "2011-11-01",
      "started": "2011-11-01T16:32:36",
      "speech_type": "ræða",
      "word_count": null,
      "excerpt": null
    },
    {
      "speech_id": "rad20111101T163303",
      "speaker": "Ragnheiður E. Árnadóttir",
      "party": null,
      "date": "2011-11-01",
      "started": "2011-11-01T16:33:03",
      "speech_type": "ræða",
      "word_count": null,
      "excerpt": null
    },
    {
      "speech_id": "rad20111101T164329",
      "speaker": "Ögmundur Jónasson",
      "party": null,
      "date": "2011-11-01",
      "started": "2011-11-01T16:43:29",
      "speech_type": "andsvar",
      "word_count": null,
      "excerpt": null
    },
    {
      "speech_id": "rad20111101T164556",
      "speaker": "Ragnheiður E. Árnadóttir",
      "party": null,
      "date": "2011-11-01",
      "started": "2011-11-01T16:45:56",
      "speech_type": "andsvar",
      "word_count": null,
      "excerpt": null
    },
    {
      "speech_id": "rad20111101T164806",
      "speaker": "Ögmundur Jónasson",
      "party": null,
      "date": "2011-11-01",
      "started": "2011-11-01T16:48:06",
      "speech_type": "andsvar",
      "word_count": null,
      "excerpt": null
    },
    {
      "speech_id": "rad20111101T165022",
      "speaker": "Ragnheiður E. Árnadóttir",
      "party": null,
      "date": "2011-11-01",
      "started": "2011-11-01T16:50:22",
      "speech_type": "andsvar",
      "word_count": null,
      "excerpt": null
    },
    {
      "speech_id": "rad20111101T165239",
      "speaker": "Mörður Árnason",
      "party": null,
      "date": "2011-11-01",
      "started": "2011-11-01T16:52:39",
      "speech_type": "andsvar",
      "word_count": null,
      "excerpt": null
    },
    {
      "speech_id": "rad20111101T165504",
      "speaker": "Ragnheiður E. Árnadóttir",
      "party": null,
      "date": "2011-11-01",
      "started": "2011-11-01T16:55:04",
      "speech_type": "andsvar",
      "word_count": null,
      "excerpt": null
    },
    {
      "speech_id": "rad20111101T165655",
      "speaker": "Mörður Árnason",
      "party": null,
      "date": "2011-11-01",
      "started": "2011-11-01T16:56:55",
      "speech_type": "andsvar",
      "word_count": null,
      "excerpt": null
    },
    {
      "speech_id": "rad20111101T165757",
      "speaker": "Ragnheiður E. Árnadóttir",
      "party": null,
      "date": "2011-11-01",
      "started": "2011-11-01T16:57:57",
      "speech_type": "andsvar",
      "word_count": null,
      "excerpt": null
    },
    {
      "speech_id": "rad20111101T170032",
      "speaker": "Árni Johnsen",
      "party": null,
      "date": "2011-11-01",
      "started": "2011-11-01T17:00:32",
      "speech_type": "ræða",
      "word_count": null,
      "excerpt": null
    },
    {
      "speech_id": "rad20111101T171059",
      "speaker": "Mörður Árnason",
      "party": null,
      "date": "2011-11-01",
      "started": "2011-11-01T17:10:59",
      "speech_type": "andsvar",
      "word_count": null,
      "excerpt": null
    },
    {
      "speech_id": "rad20111101T171316",
      "speaker": "Árni Johnsen",
      "party": null,
      "date": "2011-11-01",
      "started": "2011-11-01T17:13:16",
      "speech_type": "andsvar",
      "word_count": null,
      "excerpt": null
    },
    {
      "speech_id": "rad20111101T171529",
      "speaker": "Mörður Árnason",
      "party": null,
      "date": "2011-11-01",
      "started": "2011-11-01T17:15:29",
      "speech_type": "andsvar",
      "word_count": null,
      "excerpt": null
    }
  ]
}
