{
  "slug": "141-745",
  "title_slug": "evropustofa",
  "session": 141,
  "issue_nr": "745",
  "issue_title": "Evrópustofa",
  "speech_count": 4,
  "speaker_count": 2,
  "total_words": 0,
  "first_date": "2013-03-08",
  "last_date": "2013-03-08",
  "althingi_url": "https://www.althingi.is/thingstorf/thingmalalistar-eftir-thingum/ferill/?ltg=141&mnr=745",
  "parties": [],
  "coalition_parties": [
    "Samfylkingin",
    "Vinstrihreyfingin - grænt framboð"
  ],
  "speakers": [
    {
      "name": "Vigdís Hauksdóttir",
      "party": null,
      "side": "",
      "speech_count": 2,
      "total_words": 0
    },
    {
      "name": "Össur Skarphéðinsson",
      "party": null,
      "side": "",
      "speech_count": 2,
      "total_words": 0
    }
  ],
  "speeches": [
    {
      "speech_id": "rad20130308T104946",
      "speaker": "Vigdís Hauksdóttir",
      "party": null,
      "side": "",
      "date": "2013-03-08",
      "started": "2013-03-08T10:49:46",
      "speech_type": "ræða",
      "word_count": null,
      "excerpt": null
    },
    {
      "speech_id": "rad20130308T105055",
      "speaker": "Össur Skarphéðinsson",
      "party": null,
      "side": "",
      "date": "2013-03-08",
      "started": "2013-03-08T10:50:55",
      "speech_type": "ræða",
      "word_count": null,
      "excerpt": null
    },
    {
      "speech_id": "rad20130308T105213",
      "speaker": "Vigdís Hauksdóttir",
      "party": null,
      "side": "",
      "date": "2013-03-08",
      "started": "2013-03-08T10:52:13",
      "speech_type": "ræða",
      "word_count": null,
      "excerpt": null
    },
    {
      "speech_id": "rad20130308T105336",
      "speaker": "Össur Skarphéðinsson",
      "party": null,
      "side": "",
      "date": "2013-03-08",
      "started": "2013-03-08T10:53:36",
      "speech_type": "ræða",
      "word_count": null,
      "excerpt": null
    }
  ]
}
